MANIFEST.in
setup.cfg
setup.py
pyMorfologik/__init__.py
pyMorfologik/morfologik.py
pyMorfologik/output_parser.py
pyMorfologik/parsing.py
pyMorfologik.egg-info/PKG-INFO
pyMorfologik.egg-info/SOURCES.txt
pyMorfologik.egg-info/dependency_links.txt
pyMorfologik.egg-info/top_level.txt
pyMorfologik/jar/morfologik1.9.jar
test/test_morfologik.py