Metadata-Version: 1.0
Name: pyMorfologik
Version: 0.2.2
Summary: Binding for Morfologik tool
Home-page: https://github.com/dmirecki/pyMorfologik
Author: Damian Mirecki
Author-email: dmirecki.dm@gmail.com
License: UNKNOWN
Keywords: morfologik
Platform: UNKNOWN
